<annotations><filename>091.JPEG</filename><folder>/Users/LuLienHsi/tensorflow-MobilenetV2-YOLOv1/YOLOv1/data/annotation/txt</folder><size><width>273</width><height>184</height><depth>3</depth></size><object><name>stopsign</name><pose>Unspecified</pose><truncated>0</truncated><difficult>0</difficult><bndbox><xmin>176.9999595</xmin><ymin>73.00006799999998</ymin><xmax>187.99994850000002</xmax><ymax>87.00007599999999</ymax></bndbox></object><object><name>stopsign</name><pose>Unspecified</pose><truncated>0</truncated><difficult>0</difficult><bndbox><xmin>47.0000895</xmin><ymin>70.999988</ymin><xmax>62.0000745</xmax><ymax>87.000076</ymax></bndbox></object></annotations>