<annotations><filename>280678590.jpg</filename><folder>/Users/LuLienHsi/tensorflow-MobilenetV2-YOLOv1/YOLOv1/data/annotation/txt</folder><size><width>500</width><height>375</height><depth>3</depth></size><object><name>car</name><pose>Unspecified</pose><truncated>0</truncated><difficult>0</difficult><bndbox><xmin>241.0</xmin><ymin>126.9999375</ymin><xmax>393.0</xmax><ymax>185.0000625</ymax></bndbox></object><object><name>car</name><pose>Unspecified</pose><truncated>0</truncated><difficult>0</difficult><bndbox><xmin>408.0</xmin><ymin>15.000187500000001</ymin><xmax>434.0</xmax><ymax>35.0000625</ymax></bndbox></object><object><name>car</name><pose>Unspecified</pose><truncated>0</truncated><difficult>0</difficult><bndbox><xmin>384.0</xmin><ymin>12.000187500000001</ymin><xmax>403.0</xmax><ymax>32.0000625</ymax></bndbox></object><object><name>car</name><pose>Unspecified</pose><truncated>0</truncated><difficult>0</difficult><bndbox><xmin>450.0</xmin><ymin>15.999937500000005</ymin><xmax>471.0</xmax><ymax>35.0000625</ymax></bndbox></object><object><name>car</name><pose>Unspecified</pose><truncated>0</truncated><difficult>0</difficult><bndbox><xmin>484.0</xmin><ymin>12.0</ymin><xmax>500.0</xmax><ymax>33.0</ymax></bndbox></object></annotations>