<annotations><filename>613388971.jpg</filename><folder>/Users/LuLienHsi/tensorflow-MobilenetV2-YOLOv1/YOLOv1/data/annotation/txt</folder><size><width>375</width><height>500</height><depth>3</depth></size><object><name>car</name><pose>Unspecified</pose><truncated>0</truncated><difficult>0</difficult><bndbox><xmin>195.0001875</xmin><ymin>414.0</ymin><xmax>284.0000625</xmax><ymax>471.0</ymax></bndbox></object><object><name>car</name><pose>Unspecified</pose><truncated>0</truncated><difficult>0</difficult><bndbox><xmin>285.99993750000004</xmin><ymin>409.0</ymin><xmax>374.9998125</xmax><ymax>478.0</ymax></bndbox></object></annotations>