<annotations><filename>FudanPed00033.png</filename><folder>/Users/LuLienHsi/tensorflow-MobilenetV2-YOLOv1/YOLOv1/data/annotation/txt</folder><size><width>396</width><height>357</height><depth>3</depth></size><object><name>person</name><pose>Unspecified</pose><truncated>0</truncated><difficult>0</difficult><bndbox><xmin>157.999842</xmin><ymin>46.9999425</ymin><xmax>308.99979</xmax><ymax>351.00007949999997</ymax></bndbox></object><object><name>person</name><pose>Unspecified</pose><truncated>0</truncated><difficult>0</difficult><bndbox><xmin>329.000166</xmin><ymin>79.99977299999998</ymin><xmax>381.000114</xmax><ymax>241.999947</ymax></bndbox></object></annotations>